<?xml version="1.0" encoding="utf-8"?>
<resources>
    <style name="Theme.App" parent="@android:style/Theme.Holo.Light">
        <item name="android:actionBarStyle">@style/Theme.App.ActionBarTheme</item>
    </style>

    <style name="Theme.App.ActionBarTheme" parent="@android:style/Widget.Holo.Light.ActionBar">
        <item name="android:background">#F16676</item>
        <item name="android:titleTextStyle">@style/Theme.App.ActionBar.Title</item>
    </style>

    <style name="Theme.App.ActionBar.Title" parent="@android:style/TextAppearance.Holo.Widget.ActionBar.Title">
        <item name="android:textColor">#00235D</item>
    </style>

</resources>
